dnsmule/__init__.py
dnsmule/baseclasses.py
dnsmule/loader.py
dnsmule/mule.py
dnsmule/backends/__init__.py
dnsmule/backends/abstract.py
dnsmule/backends/dnspython.py
dnsmule/backends/noop.py
dnsmule/definitions/__init__.py
dnsmule/definitions/domain.py
dnsmule/definitions/record.py
dnsmule/definitions/result.py
dnsmule/definitions/rrtype.py
dnsmule/definitions/tag.py
dnsmule/logger/__init__.py
dnsmule/logger/logger.py
dnsmule/plugins/__init__.py
dnsmule/plugins/abstract.py
dnsmule/plugins/noop.py
dnsmule/rules/__init__.py
dnsmule/rules/entities.py
dnsmule/rules/factories.py
dnsmule/rules/rules.py
dnsmule/rules/ruletypes.py
dnsmule/storages/__init__.py
dnsmule/storages/abstract.py
dnsmule/storages/dictstorage.py
dnsmule/storages/mongodbstorage.py
dnsmule/storages/redisstorage.py
dnsmule/utils/__init__.py
dnsmule/utils/misc.py
dnsmule-0.5.0.dist-info/LICENSE
dnsmule-0.5.0.dist-info/METADATA
dnsmule-0.5.0.dist-info/WHEEL
dnsmule-0.5.0.dist-info/top_level.txt
dnsmule-0.5.0.dist-info/RECORD
