Metadata-Version: 2.1
Name: dnsmule
Version: 0.5.0
Summary: Rule based dependency scanning and service fingerprinting via DNS
Home-page: https://github.com/joniumGit/dnsmule
Author: joniumGit
Author-email: 52005121+joniumGit@users.noreply.github.com
License: MIT
Project-URL: Bug Reports, https://github.com/joniumGit/dnsmule/issues
Project-URL: Source, https://github.com/joniumGit/dnsmule
Keywords: DNS,Dependency,DNSMule
Classifier: License :: OSI Approved :: MIT License
Classifier: Programming Language :: Python :: 3
Classifier: Development Status :: 3 - Alpha
Classifier: Intended Audience :: Science/Research
Classifier: Intended Audience :: Developers
Classifier: Topic :: Internet
Requires-Python: >=3.7
License-File: LICENSE
Requires-Dist: pyyaml
Provides-Extra: dev
Requires-Dist: pytest ; extra == 'dev'
Requires-Dist: pytest-cov ; extra == 'dev'
Requires-Dist: redis ; extra == 'dev'
Requires-Dist: pymongo ; extra == 'dev'
Requires-Dist: dnspython ; extra == 'dev'
Provides-Extra: full
Requires-Dist: redis ; extra == 'full'
Requires-Dist: pymongo ; extra == 'full'
Requires-Dist: dnspython ; extra == 'full'
